skillmap/__init__.py
skillmap/main.py
skillmap/nodes/__init__.py
skillmap/nodes/common.py
skillmap/nodes/group_node.py
skillmap/nodes/progress_bar.py
skillmap/nodes/skill_node.py
skillmap/nodes/skillmap_node.py
skillmap/skillmap_parser.py
skillmap/theme_loader.py
skillmap/themes/earth.theme
skillmap/themes/grape.theme
skillmap/themes/grass.theme
skillmap/themes/ocean.theme
skillmap/themes/pale.theme
skillmap/themes/rose.theme
skillmap-0.3.0.dist-info/entry_points.txt
skillmap-0.3.0.dist-info/LICENSE
skillmap-0.3.0.dist-info/WHEEL
skillmap-0.3.0.dist-info/METADATA
skillmap-0.3.0.dist-info/RECORD
