Metadata-Version: 2.1
Name: skillmap
Version: 0.3.0
Summary: Skillmap generates a skill tree from a toml file
Home-page: https://github.com/niyue/skillmap
License: MIT
Author: Yue Ni
Author-email: niyue.com@gmail.com
Requires-Python: >=3.8,<4.0
Classifier: License :: OSI Approved :: MIT License
Classifier: Programming Language :: Python :: 3
Classifier: Programming Language :: Python :: 3.10
Classifier: Programming Language :: Python :: 3.8
Classifier: Programming Language :: Python :: 3.9
Requires-Dist: toml (>=0.10.2,<0.11.0)
Project-URL: Repository, https://github.com/niyue/skillmap
